endlessparser/__init__.py
endlessparser/globals.py
endlessparser/parse.py
endlessparser/write.py
endlessparser/datatypes/Basic.py
endlessparser/datatypes/Map.py
endlessparser/datatypes/__init__.py
EndlessParser-0.3.dist-info/LICENSE
EndlessParser-0.3.dist-info/METADATA
EndlessParser-0.3.dist-info/WHEEL
EndlessParser-0.3.dist-info/top_level.txt
EndlessParser-0.3.dist-info/RECORD
