Metadata-Version: 2.1
Name: EndlessParser
Version: 0.3
Summary: A robust Parser for Endless Sky's data files.
Home-page: https://github.com/EndlessSkyCommunity/EndlessParser
Author: MCOfficer
Author-email: mcofficer@gmx.de
License: GPLv3+
Platform: UNKNOWN
Classifier: Development Status :: 4 - Beta
Classifier: Intended Audience :: Developers
Classifier: License :: OSI Approved :: GNU General Public License v3 or later (GPLv3+)
Classifier: Operating System :: OS Independent
Classifier: Programming Language :: Python :: 3.7
Classifier: Topic :: Text Processing
Requires-Python: >=3.7
